auth_proxy/__init__.py
auth_proxy/config.py
auth_proxy/hash_password.py
auth_proxy/main.py
auth_proxy/proxy.py
auth_proxy/validate.py
auth_proxy/auth_plugins/__init__.py
auth_proxy/auth_plugins/base.py
auth_proxy/auth_plugins/basic.py
python_auth_proxy-0.3.4.dist-info/METADATA
python_auth_proxy-0.3.4.dist-info/WHEEL
python_auth_proxy-0.3.4.dist-info/entry_points.txt
python_auth_proxy-0.3.4.dist-info/licenses/LICENSE
python_auth_proxy-0.3.4.dist-info/RECORD
