Metadata-Version: 2.4
Name: python-auth-proxy
Version: 0.3.4
Summary: Modular authenticating reverse proxy
Project-URL: Homepage, https://git.private.coffee/kumi/auth-proxy
Project-URL: Bug Tracker, https://git.private.coffee/kumi/auth-proxy/issues
Author-email: Kumi Mitterer <auth-proxy@kumi.email>
License: MIT
License-File: LICENSE
Classifier: Development Status :: 4 - Beta
Classifier: Intended Audience :: System Administrators
Classifier: License :: OSI Approved :: MIT License
Classifier: Programming Language :: Python :: 3
Classifier: Programming Language :: Python :: 3.10
Classifier: Programming Language :: Python :: 3.11
Classifier: Programming Language :: Python :: 3.12
Classifier: Programming Language :: Python :: 3.13
Classifier: Topic :: Internet :: WWW/HTTP :: HTTP Servers
Classifier: Topic :: Security
Requires-Python: >=3.8
Requires-Dist: aiohttp
Requires-Dist: bcrypt
Requires-Dist: pyyaml
Requires-Dist: requests
